{
  "itemid": "minecraft:paper",
  "displayname": "§aMedium Huntrap",
  "nbttag": "{ExtraAttributes:{id:\"RETIA_MELIORA\"},HideFlags:254,ItemModel:\"hypixel_skyblock:item/island_relevant/foraging_2/traps/medium_huntrap\",display:{Lore:[0:\"§8Hunting Tool\",1:\"\",2:\"§6Ability: Retentio  §e§lRIGHT CLICK\",3:\"§cTraps §7can be placed near the spawn\",4:\"§7location of a §9Shard §7creature, with\",5:\"§7time it will eventually catch it.\",6:\"\",7:\"§6Ability: Meliora \",8:\"§7Reduces the time to capture by §c10%§7.\",9:\"\",10:\"§8§oUbi ars naturam superat.\",11:\"\",12:\"§4❣ §cRequires §aHunting Skill 5§c.\",13:\"§a§lUNCOMMON TRAP\"],Name:\"§aMedium Huntrap\"}}",
  "damage": 0,
  "lore": [
    "§8Hunting Tool",
    "",
    "§6Ability: Retentio  §e§lRIGHT CLICK",
    "§cTraps §7can be placed near the spawn",
    "§7location of a §9Shard §7creature, with",
    "§7time it will eventually catch it.",
    "",
    "§6Ability: Meliora ",
    "§7Reduces the time to capture by §c10%§7.",
    "",
    "§8§oUbi ars naturam superat.",
    "",
    "§4❣ §cRequires §aHunting Skill 5§c.",
    "§a§lUNCOMMON TRAP"
  ],
  "internalname": "RETIA_MELIORA",
  "clickcommand": "",
  "crafttext": "",
  "modver": "Firmament 44.2.0-dev+mc26.1.2+g00fd3323",
  "infoType": "WIKI_URL",
  "info": [
    "https://hypixelskyblock.minecraft.wiki/w/Medium_Huntrap",
    "https://wiki.hypixel.net/Medium_Huntrap"
  ],
  "recipes": [
    {
      "A1": "TENDER_WOOD:8",
      "A2": "ENCHANTED_FIG_LOG:4",
      "A3": "TENDER_WOOD:8",
      "B1": "ENCHANTED_FIG_LOG:4",
      "B2": "RETIA_BASICA:1",
      "B3": "ENCHANTED_FIG_LOG:4",
      "C1": "TENDER_WOOD:8",
      "C2": "ENCHANTED_FIG_LOG:4",
      "C3": "TENDER_WOOD:8",
      "type": "crafting",
      "count": 1,
      "overrideOutputId": "RETIA_MELIORA"
    }
  ]
}