{
  "itemid": "minecraft:paper",
  "displayname": "§6Signal Enhancer",
  "nbttag": "{ExtraAttributes:{id:\"SIGNAL_ENHANCER\"},HideFlags:254,ItemModel:\"hypixel_skyblock:item/island_relevant/foraging_2/signal_enhancer\",display:{Lore:[0:\"§7A marvelous piece of technology,\",1:\"§7rumored to enhance the capabilities\",2:\"§7of a beacon.\",3:\"\",4:\"§6§lLEGENDARY\"],Name:\"§6Signal Enhancer\"}}",
  "damage": 0,
  "lore": [
    "§7A marvelous piece of technology,",
    "§7rumored to enhance the capabilities",
    "§7of a beacon.",
    "",
    "§6§lLEGENDARY"
  ],
  "internalname": "SIGNAL_ENHANCER",
  "clickcommand": "",
  "crafttext": "",
  "modver": "Firmament 44.2.0-dev+mc26.1.2+g00fd3323",
  "infoType": "WIKI_URL",
  "info": [
    "https://hypixelskyblock.minecraft.wiki/w/Signal_Enhancer",
    "https://wiki.hypixel.net/Signal_Enhancer"
  ]
}